[{"candidateOpenAlexId":"I4210152903","candidateOpenAlexName":"General Electric (Norway)","countyIds":["39"],"fundingNok":101907954,"institutionLegalName":"GE VINGMED ULTRASOUND AS","institutionShortName":"GE","reason":"Ambiguous short-name match; excluded until audited against a direct OpenAlex mapping."},{"candidateOpenAlexId":"I4210152903","candidateOpenAlexName":"General Electric (Norway)","countyIds":["03"],"fundingNok":48059000,"institutionLegalName":"GE HEALTHCARE AS","institutionShortName":"GE","reason":"Ambiguous short-name match; excluded until audited against a direct OpenAlex mapping."},{"candidateOpenAlexId":"I4210152903","candidateOpenAlexName":"General Electric (Norway)","countyIds":["42"],"fundingNok":2886637,"institutionLegalName":"GE HEALTHCARE AS AVD LINDESNES","institutionShortName":"GE","reason":"Ambiguous short-name match; excluded until audited against a direct OpenAlex mapping."}]
